odoo/addons/l10n_fi_business_code_validate/README.rst
odoo/addons/l10n_fi_business_code_validate/__init__.py
odoo/addons/l10n_fi_business_code_validate/__manifest__.py
odoo/addons/l10n_fi_business_code_validate/i18n/fi.po
odoo/addons/l10n_fi_business_code_validate/i18n/l10n_fi_business_code_validate.pot
odoo/addons/l10n_fi_business_code_validate/models/__init__.py
odoo/addons/l10n_fi_business_code_validate/models/res_partner.py
odoo/addons/l10n_fi_business_code_validate/readme/CONFIGURE.rst
odoo/addons/l10n_fi_business_code_validate/readme/CONTRIBUTORS.rst
odoo/addons/l10n_fi_business_code_validate/readme/CREDITS.rst
odoo/addons/l10n_fi_business_code_validate/readme/DESCRIPTION.rst
odoo/addons/l10n_fi_business_code_validate/readme/HISTORY.rst
odoo/addons/l10n_fi_business_code_validate/readme/MAINTAINER.rst
odoo/addons/l10n_fi_business_code_validate/static/description/icon.png
odoo/addons/l10n_fi_business_code_validate/static/description/index.html
odoo/addons/l10n_fi_business_code_validate/tests/__init__.py
odoo/addons/l10n_fi_business_code_validate/tests/test_business_code_validate.py
odoo14_addon_l10n_fi_business_code_validate-14.0.1.0.1.dev4.dist-info/METADATA
odoo14_addon_l10n_fi_business_code_validate-14.0.1.0.1.dev4.dist-info/WHEEL
odoo14_addon_l10n_fi_business_code_validate-14.0.1.0.1.dev4.dist-info/top_level.txt
odoo14_addon_l10n_fi_business_code_validate-14.0.1.0.1.dev4.dist-info/RECORD
